notion_database/__init__.py
notion_database/children.py
notion_database/color.py
notion_database/cover.py
notion_database/database.py
notion_database/icon.py
notion_database/page.py
notion_database/properties.py
notion_database/query.py
notion_database/request.py
notion_database/search.py
utils/__init__.py
utils/deprecate.py
notion_database-20220628.8.dist-info/LICENSE
notion_database-20220628.8.dist-info/METADATA
notion_database-20220628.8.dist-info/WHEEL
notion_database-20220628.8.dist-info/top_level.txt
notion_database-20220628.8.dist-info/RECORD
