Metadata-Version: 2.1
Name: notion-database
Version: 20220628.8
Summary: Notion API Database Python Implementation
Home-page: https://github.com/minwook-shin/notion-database
Author: minwook-shin
Author-email: minwook0106@gmail.com
Project-URL: Bug Tracker, https://github.com/minwook-shin/notion-database/issues
Classifier: Programming Language :: Python :: 3
Classifier: License :: OSI Approved :: GNU General Public License v3 (GPLv3)
Classifier: Operating System :: OS Independent
Requires-Python: >=3.7
License-File: LICENSE
Requires-Dist: requests (==2.28.2)
Requires-Dist: typing-extensions (==4.5.0)
